app/__init__.py
app/connection.py
app/core/__init__.py
app/core/base.py
app/core/core.py
app/core/models.py
app/helpers.py
app/logic.py
app/models.py
app/tests/__init__.py
app/tests/test.py
lesson18_poetry-0.1.1.dist-info/METADATA
lesson18_poetry-0.1.1.dist-info/WHEEL
lesson18_poetry-0.1.1.dist-info/RECORD
