Metadata-Version: 2.1
Name: lesson18-poetry
Version: 0.1.1
Summary: 
Author: ig.rudenko
Author-email: ig.rudenko@users.noreply.github.com
Requires-Python: >=3.10,<4.0
Classifier: Programming Language :: Python :: 3
Classifier: Programming Language :: Python :: 3.10
Classifier: Programming Language :: Python :: 3.11
Requires-Dist: aiohttp (>=3.8.4,<4.0.0)
Requires-Dist: pyyaml (>=6.0,<7.0)
Requires-Dist: requests (>=2.29.0,<3.0.0)
Requires-Dist: sqlalchemy (>=2.0.12,<3.0.0)
